{
  "gitSyncId": "69f5b2cc9bd3e26211482972_c8e00581-42ad-4499-939a-104e4fe613c0",
  "id": "Список задач_q_delete_task",
  "pluginId": "postgres-plugin",
  "pluginType": "DB",
  "unpublishedAction": {
    "actionConfiguration": {
      "body": "WITH v AS (\n  SELECT NULLIF(CAST({{ Table1.selectedRow.ID || '' }} AS text), '')::bigint AS task_id\n)\nDELETE FROM tasks t\nUSING v\nWHERE t.id = v.task_id\nRETURNING t.id;\n",
      "encodeParamsToggle": true,
      "paginationType": "NONE",
      "pluginSpecifiedTemplates": [
        {
          "value": true
        }
      ],
      "timeoutInMillisecond": 10000
    },
    "confirmBeforeExecute": false,
    "datasource": {
      "id": "tax_control datasource 1",
      "isAutoGenerated": false,
      "name": "tax_control datasource 1",
      "pluginId": "postgres-plugin"
    },
    "dynamicBindingPathList": [
      {
        "key": "body"
      }
    ],
    "name": "q_delete_task",
    "pageId": "Список задач",
    "runBehaviour": "MANUAL",
    "userSetOnLoad": false
  }
}